{
  "MTC": [
    { "code": 1,
      "name":"Иван",
      "otch":"Иванович",
      "fam":"Иванов",
      "balance":200
    },
    {
      "code": 2,
      "name":"Сидор",
      "otch":"Сидорович",
      "fam":"Сидоров",
      "balance":250
    },
    {
      "code": 3,
      "name":"Пётр",
      "otch":"Петрович",
      "fam":"Петров",
      "balance":180
    },
    {
      "code": 4,
      "name":"Григорий",
      "otch":"Григорьевич",
      "fam":"Григорьев",
      "balance":-120
    }
  ],

  "Velcome": [
    { "code": 5,
      "name":"Сергей",
      "otch":"Сергеевич",
      "fam":"Сергеев",
      "balance":320
    },
    {
      "code": 6,
      "name":"Алексей",
      "otch":"Алексеевчи",
      "fam":"Алексеев",
      "balance":-40
    },
    {
      "code": 7,
      "name":"Игнат",
      "otch":"Игнатович",
      "fam":"Игнатов",
      "balance":210
    },
    {
      "code": 8,
      "name":"Андрей",
      "otch":"Андреевич",
      "fam":"Андреев",
      "balance":-165
    }
  ]
}

